LICENSE
MANIFEST.in
README
chiki_media.py
setup.py
chiki_media.egg-info/PKG-INFO
chiki_media.egg-info/SOURCES.txt
chiki_media.egg-info/dependency_links.txt
chiki_media.egg-info/not-zip-safe
chiki_media.egg-info/requires.txt
chiki_media.egg-info/top_level.txt