Metadata-Version: 1.0
Name: chiki-media
Version: 0.0.1
Summary: chiki media libs.
Home-page: https://github.com/endsh/chiki-media
Author: Linshao
Author-email: 438985635@qq.com
License: UNKNOWN
Platform: any
